<?xml version="1.0" encoding="utf-8"?>
<XnaContent>
  <Asset Type="ProjectMercury.ParticleEffect">
    <Item>
      <Name>Emitter01</Name>
      <Budget>10</Budget>
      <Term>0.5</Term>
      <ReleaseQuantity>5</ReleaseQuantity>
      <Enabled>true</Enabled>
      <ReleaseSpeed>
        <Value>100</Value>
        <Variation>200</Variation>
      </ReleaseSpeed>
      <ReleaseColour>
        <Value>1 1 1</Value>
        <Variation>0 0 0</Variation>
      </ReleaseColour>
      <ReleaseOpacity>
        <Value>1</Value>
        <Variation>0</Variation>
      </ReleaseOpacity>
      <ReleaseScale>
        <Value>10</Value>
        <Variation>5</Variation>
      </ReleaseScale>
      <ReleaseRotation>
        <Value>0</Value>
        <Variation>0</Variation>
      </ReleaseRotation>
      <ReleaseImpulse>0 0</ReleaseImpulse>
      <ParticleTextureAssetName>particules/FlowerBurst</ParticleTextureAssetName>
      <Modifiers>
        <Item Type="ProjectMercury.Modifiers.ScaleModifier">
          <InitialScale>50</InitialScale>
          <UltimateScale>20</UltimateScale>
        </Item>
        <Item Type="ProjectMercury.Modifiers.OpacityModifier">
          <Initial>1</Initial>
          <Ultimate>0</Ultimate>
        </Item>
      </Modifiers>
      <BlendMode>Add</BlendMode>
      <TriggerOffset>0 0</TriggerOffset>
      <MinimumTriggerPeriod>0</MinimumTriggerPeriod>
    </Item>
    <Item Type="ProjectMercury.Emitters.CircleEmitter">
      <Name>Emitter05</Name>
      <Budget>1</Budget>
      <Term>0.25</Term>
      <ReleaseQuantity>1</ReleaseQuantity>
      <Enabled>true</Enabled>
      <ReleaseSpeed>
        <Value>0</Value>
        <Variation>0</Variation>
      </ReleaseSpeed>
      <ReleaseColour>
        <Value>1 1 1</Value>
        <Variation>0 0 0</Variation>
      </ReleaseColour>
      <ReleaseOpacity>
        <Value>1</Value>
        <Variation>0</Variation>
      </ReleaseOpacity>
      <ReleaseScale>
        <Value>100</Value>
        <Variation>10</Variation>
      </ReleaseScale>
      <ReleaseRotation>
        <Value>0</Value>
        <Variation>0</Variation>
      </ReleaseRotation>
      <ReleaseImpulse>0 0</ReleaseImpulse>
      <ParticleTextureAssetName>particules/FlowerBurst</ParticleTextureAssetName>
      <Modifiers />
      <BlendMode>Add</BlendMode>
      <TriggerOffset>0 0</TriggerOffset>
      <MinimumTriggerPeriod>0</MinimumTriggerPeriod>
      <Radius>10</Radius>
      <Ring>true</Ring>
      <Radiate>false</Radiate>
    </Item>
    <Name>Particle Effect</Name>
    <Author>None</Author>
    <Description>None</Description>
  </Asset>
</XnaContent>